LICENSE.md
MANIFEST.in
README.md
setup.cfg
setup.py
src/bcr_api/__init__.py
src/bcr_api/authenticate.py
src/bcr_api/bwdata.py
src/bcr_api/bwproject.py
src/bcr_api/bwresources.py
src/bcr_api/credentials.py
src/bcr_api/filters.py
src/bcr_api.egg-info/PKG-INFO
src/bcr_api.egg-info/SOURCES.txt
src/bcr_api.egg-info/dependency_links.txt
src/bcr_api.egg-info/entry_points.txt
src/bcr_api.egg-info/requires.txt
src/bcr_api.egg-info/top_level.txt
src/bcr_api/.ipynb_checkpoints/bwdata-checkpoint.py
src/bcr_api/.ipynb_checkpoints/bwproject-checkpoint.py
src/bcr_api/.ipynb_checkpoints/bwresources-checkpoint.py
src/bcr_api/.ipynb_checkpoints/filters-checkpoint.py
test/test_bwproject.py
test/test_credentials.py
test/test_id_name_map.py