Metadata-Version: 2.1
Name: bcr-api
Version: 1.5.0
Summary: A client library for the Brandwatch Consumer Research API
Home-page: https://github.com/BrandwatchLtd/bcr-api
Author: Paul Siegel, Matthew Franglen, Colin Sullivan, Hamish Morgan and Peter Fairfax
Author-email: paul@brandwatch.com, matthew@brandwatch.com, csullivan@brandwatch.com, peterf@brandwatch.com
License: License :: OSI Approved :: MIT License
Classifier: Development Status :: 5 - Production/Stable
Classifier: Intended Audience :: Developers
Classifier: License :: OSI Approved :: MIT License
Classifier: Programming Language :: Python :: 3
Classifier: Programming Language :: Python :: 3.5
Classifier: Programming Language :: Python :: 3.6
Classifier: Programming Language :: Python :: 3.7
Classifier: Programming Language :: Python :: 3.8
Requires-Python: >=3.5
License-File: LICENSE.md
